2A/FPGA/fournitures/ER_1OCTET/er_1octet.vhd
library IEEE;
use IEEE.STD_LOGIC_1164.ALL;

entity er_1octet is
  port ( rst : in std_logic ;
         clk : in std_logic ;
         en : in std_logic ;
         din : in std_logic_vector (7 downto 0) ;
         miso : in std_logic ;
         sclk : out std_logic ;
         mosi : out std_logic ;
         dout : out std_logic_vector (7 downto 0) ;
         busy : out std_logic);
end er_1octet;

architecture Behavioral of er_1octet is
 -- États possibles 
    type t_etat is (idle,bits_emis,bits_reception);
    
    -- État actuel
    signal etat : t_etat;
begin

 er : process (clk, rst)
  variable cpt: integer :=7;
  variable registre : std_logic_vector(7 downto 0) :=(others => '0');
  
 begin
       
        if(rst = '0') then
            -- réinitialisation des variables du process
            -- et des signaux calculés par le process
				etat <= idle;
            sclk <= '1'; 
            -- Mise à zéro de tous les signaux et variables
            mosi <= '0';
            dout <= "00000000";
            busy <= '0';
            cpt := 0;
            registre := "00000000";
				
				 elsif(rising_edge(clk)) then 
                  case etat is
						when idle =>
                        -- état d'attente d'un ordre d'envoi

                      if(en = '1') then
								  busy <= '1';
					      	-- mémoriser din pour être sûr qu'elle ne change pas
						        registre := din;
						        --dout <= (others => '0');
						      -- placer (envoyer) le 1er bit
						      cpt:= 7;
						      mosi <= registre(7); 
						      etat <= bits_emis;
								-- on place sclk a 0
								sclk <= '0';
						    end if; --en
							 
						 when bits_emis =>
						  sclk <= '1'; -- stock la valeur du bits recu
                    registre(cpt) := miso;
						  -- dout(8-(cpt+1)) <= miso;
                            -- on envoie les données 
						      if(cpt > 0) then
                              -- Changement d'état
                                etat <= bits_reception;
                            else 
                                -- le cpt repasse à 0
                                busy <= '0';
                                dout <= registre;
                                -- on change d'état
                                etat <= idle;
                            end if;
									 
						 when bits_reception =>
						          -- Décrementation de cpt                      
                                cpt := cpt - 1;
                                sclk <= '0';
                                mosi <= registre(cpt);
                                -- changement d'état
                                etat <= bits_emis;
                  end case;
             end if;
    end process;         
end Behavioral;

2A/FPGA/fournitures/ER_1OCTET/test_er_1octet_simple.vhd
library IEEE;
use IEEE.STD_LOGIC_1164.ALL;

entity test_er_1octet is
  end test_er_1octet;

architecture behavior of test_er_1octet is

  component er_1octet
    port ( rst : in std_logic;
           clk : in std_logic;
           en : in std_logic;
           din : in std_logic_vector (7 downto 0);
           miso : in std_logic;
           sclk : out std_logic;
           mosi : out std_logic;
           dout : out std_logic_vector (7 downto 0);
           busy : out std_logic);
  end component;

  --Inputs
  signal clk : std_logic := '0';
  signal reset : std_logic := '0';
  signal en : std_logic := '0';
  signal din : std_logic_vector(7 downto 0) := (others => '0');
  signal miso : std_logic := '0';

  --Outputs
  signal busy : std_logic;
  signal dout : std_logic_vector(7 downto 0);
  signal sclk : std_logic;
  signal mosi : std_logic;

  --References
  signal busy_ref : std_logic;
  signal dout_ref : std_logic_vector(7 downto 0);
  signal sclk_ref : std_logic;
  signal mosi_ref : std_logic;

  -- Clock period definitions
  constant clk_period : time := 10 ns;

begin

  m : er_1octet
  port map ( clk => clk,
             rst => reset,
             en => en,
             busy => busy,
             din => din,
             dout => dout,
             sclk => sclk,
             miso => miso,
             mosi => mosi
           );

  
    -- insert stimulus here

   

  genere_miso : process(clk, reset)

    variable cpt : natural;

  begin

    if(reset = '0') then
      miso <= '0';
      cpt := 0;
    elsif(falling_edge(clk)) then
      cpt := (cpt + 1) mod 7;
      if(cpt < 3) then
        miso <= '0';
      else
        miso <= '1';
      end if;                  
    end if;

  end process genere_miso;

  --
  -- pour vérifier si mosi, sclk et busy et dout sont corrects

  busy_ref <= '0' after 0 ps,
              '1' after 205000 ps,
              '0' after 355000 ps,
              '1' after 425000 ps,
              '0' after 575000 ps;

  dout_ref <= "00000000" after 0 ps,
              "10011011" after 355000 ps,
              "10110011" after 575000 ps;

  mosi_ref <= '0' after 0 ps,
              '1' after 205000 ps,
              '0' after 225000 ps,
              '1' after 245000 ps,
              '0' after 285000 ps,
              '1' after 305000 ps,
              '0' after 325000 ps,
              '1' after 345000 ps,
              '0' after 425000 ps,
              '1' after 465000 ps,
              '0' after 505000 ps,
              '1' after 525000 ps,
              '0' after 545000 ps;

  sclk_ref <= '1' after 0 ps,
              '0' after 205000 ps,
              '1' after 215000 ps,
              '0' after 225000 ps,
              '1' after 235000 ps,
              '0' after 245000 ps,
              '1' after 255000 ps,
              '0' after 265000 ps,
              '1' after 275000 ps,
              '0' after 285000 ps,
              '1' after 295000 ps,
              '0' after 305000 ps,
              '1' after 315000 ps,
              '0' after 325000 ps,
              '1' after 335000 ps,
              '0' after 345000 ps,
              '1' after 355000 ps,
              '0' after 425000 ps,
              '1' after 435000 ps,
              '0' after 445000 ps,
              '1' after 455000 ps,
              '0' after 465000 ps,
              '1' after 475000 ps,
              '0' after 485000 ps,
              '1' after 495000 ps,
              '0' after 505000 ps,
              '1' after 515000 ps,
              '0' after 525000 ps,
              '1' after 535000 ps,
              '0' after 545000 ps,
              '1' after 555000 ps,
              '0' after 565000 ps,
              '1' after 575000 ps;

  process(clk)
  begin
    if(falling_edge(clk)) then
      assert(mosi = mosi_ref) report "mosi faux"
      severity error;
      assert(sclk = sclk_ref) report "sclk faux"
      severity error;
      assert(busy = busy_ref) report "busy faux"
      severity error;
      assert(dout = dout_ref) report "dout faux"
      severity error;
    end if;
  end process;

end behavior;

2A/FPGA/fournitures/ER_1OCTET/output.vcd
$date
   Wed Oct 27 15:04:43 2021
$end
$version
  P.20131013
$end
$timescale
  1ps
$end
$scope module test_er_1octet $end
$var wire 1 D clk $end
$var wire 1 C reset $end
$var wire 1 E en $end
$var wire 1 M din [7] $end
$var wire 1 L din [6] $end
$var wire 1 K din [5] $end
$var wire 1 J din [4] $end
$var wire 1 I din [3] $end
$var wire 1 H din [2] $end
$var wire 1 G din [1] $end
$var wire 1 F din [0] $end
$var wire 1 N miso $end
$var wire 1 Y busy $end
$var wire 1 X dout [7] $end
$var wire 1 W dout [6] $end
$var wire 1 V dout [5] $end
$var wire 1 U dout [4] $end
$var wire 1 T dout [3] $end
$var wire 1 S dout [2] $end
$var wire 1 R dout [1] $end
$var wire 1 Q dout [0] $end
$var wire 1 O sclk $end
$var wire 1 P mosi $end
$var wire 1 8 busy_ref $end
$var wire 1 @ dout_ref [7] $end
$var wire 1 ? dout_ref [6] $end
$var wire 1 > dout_ref [5] $end
$var wire 1 = dout_ref [4] $end
$var wire 1 < dout_ref [3] $end
$var wire 1 ; dout_ref [2] $end
$var wire 1 : dout_ref [1] $end
$var wire 1 9 dout_ref [0] $end
$var wire 1 A sclk_ref $end
$var wire 1 B mosi_ref $end
$scope module m $end
$var wire 1 C rst $end
$var wire 1 D clk $end
$var wire 1 E en $end
$var wire 1 M din [7] $end
$var wire 1 L din [6] $end
$var wire 1 K din [5] $end
$var wire 1 J din [4] $end
$var wire 1 I din [3] $end
$var wire 1 H din [2] $end
$var wire 1 G din [1] $end
$var wire 1 F din [0] $end
$var wire 1 N miso $end
$var wire 1 O sclk $end
$var wire 1 P mosi $end
$var wire 1 X dout [7] $end
$var wire 1 W dout [6] $end
$var wire 1 V dout [5] $end
$var wire 1 U dout [4] $end
$var wire 1 T dout [3] $end
$var wire 1 S dout [2] $end
$var wire 1 R dout [1] $end
$var wire 1 Q dout [0] $end
$var wire 1 Y busy $end
$upscope $end
$upscope $end
$enddefinitions $end
#0
$dumpvars
0D
0C
0E
0M
0L
0K
0J
0I
0H
0G
0F
0N
xY
xX
xW
xV
xU
xT
xS
xR
xQ
xO
xP
08
0@
0?
0>
0=
0<
0;
0:
09
1A
0B
$end
#5000
1D
#10000
0D
#15000
1D
#20000
0D
#25000
1D
#30000
0D
#35000
1D
#40000
0D
#45000
1D
#50000
0D
#55000
1D
#60000
0D
#65000
1D
#70000
0D
#75000
1D
#80000
0D
#85000
1D
#90000
0D
#95000
1D
#100000
0D
1C
#105000
1D
#110000
0D
#115000
1D
#120000
0D
1N
#125000
1D
#130000
0D
#135000
1D
#140000
0D
#145000
1D
#150000
0D
#155000
1D
#160000
0D
0N
#165000
1D
#170000
0D
#175000
1D
#180000
0D
#185000
1D
#190000
0D
1N
#195000
1D
#200000
0D
1E
1M
1K
1J
1H
1F
#205000
1D
18
0A
1B
#210000
0D
0E
xM
xL
xK
xJ
xI
xH
xG
xF
#215000
1D
1A
#220000
0D
#225000
1D
0A
0B
#230000
0D
0N
#235000
1D
1A
#240000
0D
#245000
1D
0A
1B
#250000
0D
#255000
1D
1A
#260000
0D
1N
#265000
1D
0A
#270000
0D
#275000
1D
1A
#280000
0D
#285000
1D
0A
0B
#290000
0D
#295000
1D
1A
#300000
0D
0N
#305000
1D
0A
1B
#310000
0D
#315000
1D
1A
#320000
0D
#325000
1D
0A
0B
#330000
0D
1N
#335000
1D
1A
#340000
0D
#345000
1D
0A
1B
#350000
0D
#355000
1D
08
1@
1=
1<
1:
19
1A
#360000
0D
#365000
1D
#370000
0D
0N
#375000
1D
#380000
0D
#385000
1D
#390000
0D
#395000
1D
#400000
0D
1N
#405000
1D
#410000
0D
#415000
1D
#420000
0D
1E
0M
0L
1K
1J
0I
1H
0G
0F
#425000
1D
18
0A
0B
#430000
0D
0E
xM
xL
xK
xJ
xI
xH
xG
xF
#435000
1D
1A
#440000
0D
0N
#445000
1D
0A
#450000
0D
#455000
1D
1A
#460000
0D
#465000
1D
0A
1B
#470000
0D
1N
#475000
1D
1A
#480000
0D
#485000
1D
0A
#490000
0D
#495000
1D
1A
#500000
0D
#505000
1D
0A
0B
#510000
0D
0N
#515000
1D
1A
#520000
0D
#525000
1D
0A
1B
#530000
0D
#535000
1D
1A
#540000
0D
1N
#545000
1D
0A
0B
#550000
0D
#555000
1D
1A
#560000
0D
#565000
1D
0A
#570000
0D
#575000
1D
08
1>
0<
1A
#580000
0D
0N
#585000
1D
#590000
0D
#595000
1D
#600000
0D
#605000
1D
#610000
0D
1N
#615000
1D
#620000
0D
#625000
1D
#630000
0D
#635000
1D
#640000
0D
#645000
1D
#650000
0D
0N
#655000
1D
#660000
0D
#665000
1D
#670000
0D
#675000
1D
#680000
0D
1N
